database_connect/__init__.py
database_connect/databases/__init__.py
database_connect/databases/cassandra.py
database_connect/databases/mongodb.py
database_connect-0.1.673.dist-info/METADATA
database_connect-0.1.673.dist-info/WHEEL
database_connect-0.1.673.dist-info/top_level.txt
database_connect-0.1.673.dist-info/RECORD
