Metadata-Version: 2.1
Name: database_connect
Version: 0.1.673
Summary: A single Package for all the database connectivities  ( E.g : MySQL, MongoDb, Cassandra)
Home-page: https://github.com/hrisikesh-neogi/Database-Connect
Author: Hrisikesh Neogi
Author-email: hrisikesh.neogi@gmail.com
Project-URL: Bug Tracker, https://github.com/hrisikesh-neogi/Database-Connect/issues
Classifier: Programming Language :: Python :: 3
Classifier: License :: OSI Approved :: MIT License
Classifier: Operating System :: OS Independent
Requires-Python: >=3.7
Requires-Dist: cassandra-driver ==3.29.0
Requires-Dist: ensure ==1.0.4
Requires-Dist: pandas ==2.0.3
Requires-Dist: pymongo ==4.6.1
Requires-Dist: pymongo[srv]
